kombilo/__init__.py
kombilo/_libkombilo.pyd
kombilo/abstractboard.py
kombilo/board.py
kombilo/custommenus.py
kombilo/default.cfg
kombilo/kombilo.py
kombilo/kombiloNG.py
kombilo/libkombilo.py
kombilo/license.rst
kombilo/msvcm90.dll
kombilo/msvcp90.dll
kombilo/msvcr90.dll
kombilo/option_editor.py
kombilo/sgf.py
kombilo/v.py
kombilo/vcomp90.dll
kombilo/data/references
kombilo/icons/123.png
kombilo/icons/abc-l.png
kombilo/icons/abc-u.png
kombilo/icons/actions-bookmark-new.png
kombilo/icons/actions-document-new.png
kombilo/icons/actions-document-open.png
kombilo/icons/actions-edit-clear.png
kombilo/icons/actions-edit-cut.png
kombilo/icons/actions-edit-find.png
kombilo/icons/actions-edit-select-all.png
kombilo/icons/actions-edit-undo.png
kombilo/icons/actions-go-home.png
kombilo/icons/actions-go-next.png
kombilo/icons/actions-go-previous.png
kombilo/icons/actions-list-add.png
kombilo/icons/actions-list-remove.png
kombilo/icons/actions-media-playback-back.png
kombilo/icons/actions-media-playback-pause.png
kombilo/icons/actions-media-playback-start.png
kombilo/icons/actions-media-seek-backward.png
kombilo/icons/actions-media-seek-forward.png
kombilo/icons/actions-media-skip-backward.png
kombilo/icons/actions-media-skip-forward.png
kombilo/icons/actions-process-stop.png
kombilo/icons/actions-system-search.png
kombilo/icons/apps-help-browser.png
kombilo/icons/apps-office-calendar.png
kombilo/icons/b.png
kombilo/icons/black-shaded.png
kombilo/icons/black.png
kombilo/icons/board.png
kombilo/icons/bw.png
kombilo/icons/devices-input-mouse.png
kombilo/icons/go-home-start.png
kombilo/icons/guess_fail.png
kombilo/icons/guess_success.png
kombilo/icons/kombilo_logo.png
kombilo/icons/places-user-trash.png
kombilo/icons/sq.png
kombilo/icons/status-dialog-error.png
kombilo/icons/tr.png
kombilo/icons/w.png
kombilo/icons/wb.png
kombilo/icons/white-shaded.png
kombilo/icons/white0.png
kombilo/icons/white1.png
kombilo-0.8.4.dist-info/DESCRIPTION.rst
kombilo-0.8.4.dist-info/METADATA
kombilo-0.8.4.dist-info/RECORD
kombilo-0.8.4.dist-info/WHEEL
kombilo-0.8.4.dist-info/entry_points.txt
kombilo-0.8.4.dist-info/metadata.json
kombilo-0.8.4.dist-info/top_level.txt
