Metadata-Version: 2.0
Name: kombilo
Version: 0.8.4
Summary: A database program for the game of go
Home-page: http://u-go.net/kombilo/
Author: Ulrich Goertz
Author-email: ug@geometry.de
License: MIT License
Platform: UNKNOWN
Classifier: Programming Language :: Python :: 2.7
Requires-Dist: Pillow
Requires-Dist: Pmw
Requires-Dist: configobj
